.gitignore
.gitreview
.pre-commit-config.yaml
LICENSE
MANIFEST.in
README.rst
changelog.rst
connmon.png
pyproject.toml
setup.cfg
setup.py
tox.ini
.tox/.pkg/lib/python3.11/site-packages/pip/_vendor/colorama/tests/__init__.py
.tox/.pkg/lib/python3.11/site-packages/pip/_vendor/colorama/tests/ansi_test.py
.tox/.pkg/lib/python3.11/site-packages/pip/_vendor/colorama/tests/ansitowin32_test.py
.tox/.pkg/lib/python3.11/site-packages/pip/_vendor/colorama/tests/initialise_test.py
.tox/.pkg/lib/python3.11/site-packages/pip/_vendor/colorama/tests/isatty_test.py
.tox/.pkg/lib/python3.11/site-packages/pip/_vendor/colorama/tests/utils.py
.tox/.pkg/lib/python3.11/site-packages/pip/_vendor/colorama/tests/winterm_test.py
.tox/pep484/lib/python3.11/site-packages/pip/_vendor/colorama/tests/__init__.py
.tox/pep484/lib/python3.11/site-packages/pip/_vendor/colorama/tests/ansi_test.py
.tox/pep484/lib/python3.11/site-packages/pip/_vendor/colorama/tests/ansitowin32_test.py
.tox/pep484/lib/python3.11/site-packages/pip/_vendor/colorama/tests/initialise_test.py
.tox/pep484/lib/python3.11/site-packages/pip/_vendor/colorama/tests/isatty_test.py
.tox/pep484/lib/python3.11/site-packages/pip/_vendor/colorama/tests/utils.py
.tox/pep484/lib/python3.11/site-packages/pip/_vendor/colorama/tests/winterm_test.py
.tox/pep484/lib/python3.11/site-packages/sqlalchemy_collectd/client/tests/__init__.py
.tox/pep484/lib/python3.11/site-packages/sqlalchemy_collectd/client/tests/test_collector.py
.tox/pep484/lib/python3.11/site-packages/sqlalchemy_collectd/client/tests/test_plugin.py
.tox/pep484/lib/python3.11/site-packages/sqlalchemy_collectd/client/tests/test_worker.py
.tox/pep484/lib/python3.11/site-packages/sqlalchemy_collectd/server/tests/__init__.py
.tox/pep484/lib/python3.11/site-packages/sqlalchemy_collectd/server/tests/test_listener.py
.tox/pep484/lib/python3.11/site-packages/sqlalchemy_collectd/tests/__init__.py
.tox/pep484/lib/python3.11/site-packages/sqlalchemy_collectd/tests/test_protocol.py
sqlalchemy_metrics.egg-info/PKG-INFO
sqlalchemy_metrics.egg-info/SOURCES.txt
sqlalchemy_metrics.egg-info/dependency_links.txt
sqlalchemy_metrics.egg-info/entry_points.txt
sqlalchemy_metrics.egg-info/requires.txt
sqlalchemy_metrics.egg-info/top_level.txt
