Metadata-Version: 2.1
Name: sqlalchemy-metrics
Version: 0.0.0
Summary: Database connection pool / transaction metrics library
Author-email: Mike Bayer <mike_mp@zzzcomputing.com>
License: Copyright 2018-2019 Michael Bayer
Keywords: sqlalchemy,collectd,prometheus
Classifier: Development Status :: 4 - Beta
Classifier: Intended Audience :: Developers
Classifier: License :: OSI Approved :: MIT License
Classifier: Programming Language :: Python
Classifier: Programming Language :: Python :: 3
Classifier: Programming Language :: Python :: 3.8
Classifier: Programming Language :: Python :: 3.9
Classifier: Programming Language :: Python :: 3.10
Classifier: Programming Language :: Python :: 3.11
Classifier: Programming Language :: Python :: 3.12
Classifier: Topic :: Database :: Front-Ends
Classifier: Operating System :: OS Independent
Requires-Python: >=3.8
License-File: LICENSE
